covimerage/__init__.py
covimerage/__main__.py
covimerage/__version__.py
covimerage/_compat.py
covimerage/cli.py
covimerage/coveragepy.py
covimerage/exceptions.py
covimerage/logger.py
covimerage/utils.py
covimerage-0.2.2.dist-info/LICENSE
covimerage-0.2.2.dist-info/METADATA
covimerage-0.2.2.dist-info/WHEEL
covimerage-0.2.2.dist-info/entry_points.txt
covimerage-0.2.2.dist-info/top_level.txt
covimerage-0.2.2.dist-info/RECORD
