Metadata-Version: 2.1
Name: covimerage
Version: 0.2.2
Summary: Generate coverage information for Vim scripts.
Home-page: https://github.com/Vimjas/covimerage
Author: Daniel Hahler
License: UNKNOWN
Platform: UNKNOWN
Classifier: License :: OSI Approved :: MIT License
Classifier: Programming Language :: Python
Classifier: Programming Language :: Python :: 2.7
Classifier: Programming Language :: Python :: 3
Classifier: Programming Language :: Python :: 3.3
Classifier: Programming Language :: Python :: 3.4
Classifier: Programming Language :: Python :: 3.5
Classifier: Programming Language :: Python :: 3.6
Classifier: Programming Language :: Python :: 3.7
Classifier: Programming Language :: Python :: 3.8
Classifier: Programming Language :: Python :: Implementation :: CPython
Classifier: Programming Language :: Python :: Implementation :: PyPy
License-File: LICENSE
Requires-Dist: attrs (>=16.1.0)
Requires-Dist: click (<7.1)
Requires-Dist: coverage (<5.0a6)
Provides-Extra: dev
Requires-Dist: pytest (>=3.3.0) ; extra == 'dev'
Requires-Dist: pytest-mock ; extra == 'dev'
Requires-Dist: flake8 (>=3.7.0) ; extra == 'dev'
Requires-Dist: isort ; extra == 'dev'
Requires-Dist: pdbpp ; extra == 'dev'
Requires-Dist: pytest-pdb ; extra == 'dev'
Provides-Extra: qa
Requires-Dist: flake8 (>=3.7.0) ; extra == 'qa'
Requires-Dist: isort ; extra == 'qa'
Provides-Extra: testing
Requires-Dist: pytest (>=3.3.0) ; extra == 'testing'
Requires-Dist: pytest-mock ; extra == 'testing'
